{"1.1.0": ["Ed Venator", "evenator@swri.edu"], "1.0.0": ["Ed Venator", "evenator@swri.edu"], "2.0.0": ["Ed Venator", "evenator@swri.edu"], "0.0.14": ["Ed Venator", "evenator@swri.edu"], "2.2.1": ["Ed Venator", "evenator@swri.edu"], "2.2.0": ["Ed Venator", "evenator@swri.edu"], "0.0.13": ["Ed Venator", "evenator@swri.edu"], "0.0.12": ["Ed Venator", "evenator@swri.edu"], "2.1.0": ["Ed Venator", "evenator@swri.edu"], "2.8.0": ["P. J. Reed", "preed@swri.edu"], "0.0.5": ["Ed Venator", "evenator@swri.edu"], "0.0.4": ["Ed Venator", "evenator@swri.edu"], "0.0.7": ["Ed Venator", "evenator@swri.edu"], "0.0.6": ["Ed Venator", "evenator@swri.edu"], "0.0.1": ["Ed Venator", "evenator@swri.edu"], "0.0.3": ["Ed Venator", "evenator@swri.edu"], "0.0.2": ["Ed Venator", "evenator@swri.edu"], "0.3.0": ["Ed Venator", "evenator@swri.edu"], "0.0.9": ["Ed Venator", "evenator@swri.edu"], "0.0.8": ["Ed Venator", "evenator@swri.edu"], "2.3.0": ["Ed Venator", "evenator@swri.edu"], "1.2.0": ["Ed Venator", "evenator@swri.edu"], "2.4.0": ["P. J. Reed", "preed@swri.edu"], "2.5.0": ["P. J. Reed", "preed@swri.edu"], "2.6.0": ["P. J. Reed", "preed@swri.edu"], "2.7.0": ["P. J. Reed", "preed@swri.edu"], "2.7.1": ["P. J. Reed", "preed@swri.edu"], "2.7.2": ["P. J. Reed", "preed@swri.edu"], "2.7.3": ["P. J. Reed", "preed@swri.edu"], "0.0.11": ["Ed Venator", "evenator@swri.edu"], "0.0.10": ["Ed Venator", "evenator@swri.edu"]}